djutil/__init__.py
djutil/autocompletes.py
djutil/models.py
djutil/str.py
Dju-23.11.27.0.dist-info/LICENSE
Dju-23.11.27.0.dist-info/METADATA
Dju-23.11.27.0.dist-info/WHEEL
Dju-23.11.27.0.dist-info/top_level.txt
Dju-23.11.27.0.dist-info/zip-safe
Dju-23.11.27.0.dist-info/RECORD
